LICENSE
README.rst
setup.py
qhsmodule/__init__.py
qhsmodule/module1.py
qhsmodule/module2.py
qhsmodule.egg-info/PKG-INFO
qhsmodule.egg-info/SOURCES.txt
qhsmodule.egg-info/dependency_links.txt
qhsmodule.egg-info/top_level.txt