Metadata-Version: 2.1
Name: qhsmodule
Version: 1.0.0
Summary: My first module
Home-page: UNKNOWN
Author: qinhaisheng
Author-email: 1849039507@qq.com
License: UNKNOWN
Platform: UNKNOWN
License-File: LICENSE
